README.md
setup.cfg
setup.py
fuo_xiami/__init__.py
fuo_xiami/api.py
fuo_xiami/excs.py
fuo_xiami/models.py
fuo_xiami/provider.py
fuo_xiami/schemas.py
fuo_xiami/ui.py
fuo_xiami.egg-info/PKG-INFO
fuo_xiami.egg-info/SOURCES.txt
fuo_xiami.egg-info/dependency_links.txt
fuo_xiami.egg-info/entry_points.txt
fuo_xiami.egg-info/requires.txt
fuo_xiami.egg-info/top_level.txt