Metadata-Version: 1.1
Name: fuo-xiami
Version: 0.2.3
Summary: feeluown xiami plugin
Home-page: https://github.com/feeluown/feeluown-xiami
Author: Cosven
Author-email: yinshaowen241@gmail.com
License: UNKNOWN
Keywords: feeluown,plugin,xiami
Platform: UNKNOWN
Classifier: Development Status :: 3 - Alpha
Classifier: Programming Language :: Python :: 3.5
Classifier: Programming Language :: Python :: 3.6
Classifier: Programming Language :: Python :: 3.7
Classifier: Programming Language :: Python :: 3 :: Only
